allauth_ui/__init__.py
allauth_ui/adapter.py
allauth_ui/admin.py
allauth_ui/forms.py
allauth_ui/locale/vi/LC_MESSAGES/django.mo
allauth_ui/locale/vi/LC_MESSAGES/django.po
allauth_ui/settings.py
allauth_ui/signals.py
allauth_ui/templates/account/account_inactive.html
allauth_ui/templates/account/base.html
allauth_ui/templates/account/email/base_message.txt
allauth_ui/templates/account/email/email_confirmation_message.txt
allauth_ui/templates/account/email/email_confirmation_signup_message.txt
allauth_ui/templates/account/email/email_confirmation_signup_subject.txt
allauth_ui/templates/account/email/email_confirmation_subject.txt
allauth_ui/templates/account/email/password_reset_key_message.txt
allauth_ui/templates/account/email/password_reset_key_subject.txt
allauth_ui/templates/account/email.html
allauth_ui/templates/account/email_change.html
allauth_ui/templates/account/email_confirm.html
allauth_ui/templates/account/home.html
allauth_ui/templates/account/locked.html
allauth_ui/templates/account/login.html
allauth_ui/templates/account/logout.html
allauth_ui/templates/account/messages/cannot_delete_primary_email.txt
allauth_ui/templates/account/messages/email_confirmation_sent.txt
allauth_ui/templates/account/messages/email_confirmed.txt
allauth_ui/templates/account/messages/email_deleted.txt
allauth_ui/templates/account/messages/logged_in.txt
allauth_ui/templates/account/messages/logged_out.txt
allauth_ui/templates/account/messages/password_changed.txt
allauth_ui/templates/account/messages/password_set.txt
allauth_ui/templates/account/messages/primary_email_set.txt
allauth_ui/templates/account/messages/unverified_primary_email.txt
allauth_ui/templates/account/password_change.html
allauth_ui/templates/account/password_reset.html
allauth_ui/templates/account/password_reset_done.html
allauth_ui/templates/account/password_reset_from_key.html
allauth_ui/templates/account/password_reset_from_key_done.html
allauth_ui/templates/account/password_set.html
django_allauth_simple_ui-0.1.2.dist-info/METADATA
django_allauth_simple_ui-0.1.2.dist-info/WHEEL
django_allauth_simple_ui-0.1.2.dist-info/RECORD
