Metadata-Version: 2.1
Name: django-allauth-simple-ui
Version: 0.1.2
Summary: Simple templates for django-allauth
Home-page: https://github.com/ThuanD/django-allauth-simple-ui
Author: kai
Author-email: thuan.dv0@gmail.com
Requires-Python: >=3.10,<4.0
Classifier: Programming Language :: Python :: 3
Classifier: Programming Language :: Python :: 3.10
Classifier: Programming Language :: Python :: 3.11
Classifier: Programming Language :: Python :: 3.12
Requires-Dist: django (>=5.1.1,<6.0.0)
Requires-Dist: django-allauth (>=65.0.2,<66.0.0)
Requires-Dist: django-bootstrap5 (>=24.3,<25.0)
Requires-Dist: jwt (>=1.3.1,<2.0.0)
Project-URL: Repository, https://github.com/ThuanD/django-allauth-simple-ui
